{"skeleton":{"hash":"Fn1LAjnnqGoGi/MxHEokNnZmWHM","spine":"3.7.94","width":647.22,"height":444.64},"bones":[{"name":"root"},{"name":"_Collision","parent":"root","x":-307.14},{"name":"_Shadow","parent":"root","scaleX":9.767},{"name":"_chr","parent":"root","x":-128.93,"scaleX":0.25,"scaleY":0.25},{"name":"Body","parent":"_chr","x":31.26,"y":-3.49},{"name":"Body2","parent":"Body","length":379.95,"rotation":116.57,"x":-54.79,"y":172.07},{"name":"Body3","parent":"Body2","length":439.16,"rotation":-43.34,"x":521.63,"y":-57.96},{"name":"Neck","parent":"Body3","x":555.77,"y":62.21},{"name":"Head","parent":"Neck","length":388.02,"rotation":100.81,"x":11.14,"y":132.7},{"name":"Mouth","parent":"Head","length":153.37,"rotation":61.68,"x":474.65,"y":139.9},{"name":"Mouth_L","parent":"Head","length":122.22,"rotation":101.49,"x":36.89,"y":100.03},{"name":"Head3","parent":"Head","length":214.8,"rotation":-59.74,"x":413.27,"y":-96.27},{"name":"Head4","parent":"Head","length":213.85,"rotation":-112.8,"x":369.63,"y":-102.84},{"name":"Body4","parent":"Body","length":393.18,"rotation":13.04,"x":188.89,"y":92.31},{"name":"Body5","parent":"Body4","length":331.32,"rotation":-34.45,"x":510.11,"y":-24.9},{"name":"Body6","parent":"Body5","length":224.25,"rotation":43.6,"x":378.24,"y":18.4},{"name":"Tale","parent":"Body6","length":372.63,"rotation":5.27,"x":256.96,"y":21.49},{"name":"Body7","parent":"Body6","length":213.78,"rotation":43.6,"x":247.34,"y":49.88},{"name":"Leg_L1","parent":"Body3","length":89.52,"rotation":-65.46,"x":422.53,"y":-118.74},{"name":"Leg_L2","parent":"Body3","length":107.59,"rotation":-86.22,"x":275.77,"y":-120.86},{"name":"Leg_L3","parent":"Body3","length":97.79,"rotation":-87.55,"x":95.2,"y":-101.58},{"name":"Leg_L4","parent":"Body2","length":102.2,"rotation":-131.42,"x":378.71,"y":-107.92},{"name":"Body12","parent":"Body2","length":140.28,"rotation":-124,"x":182.17,"y":-54.73},{"name":"Body13","parent":"Body2","length":134.76,"rotation":-155.49,"x":28,"y":-115.14},{"name":"Leg14","parent":"Body4","length":95.01,"rotation":-120.32,"x":55.77,"y":-27.71},{"name":"Leg15","parent":"Body4","length":111.83,"rotation":-47.02,"x":157.42,"y":-48.25},{"name":"Leg16","parent":"Body4","length":112.97,"rotation":-47.86,"x":281.36,"y":-56.95},{"name":"Leg17","parent":"Body5","length":85.77,"rotation":-45.03,"x":-35.98,"y":-72.68},{"name":"Leg18","parent":"Body5","length":75.27,"rotation":-48.21,"x":64.89,"y":-41.39},{"name":"Leg19","parent":"Body5","length":68.46,"rotation":-54.96,"x":228.22,"y":-27.15},{"name":"Leg20","parent":"Body5","length":70.79,"rotation":-48.6,"x":324.67,"y":8.51},{"name":"Leg21","parent":"Body6","length":67.03,"rotation":-54.76,"x":49.06,"y":-11.08},{"name":"Body8","parent":"Body3","length":149.5,"rotation":112.3,"x":355.55,"y":85.04},{"name":"Body9","parent":"Body3","length":125.26,"rotation":84.79,"x":157.21,"y":52.84},{"name":"Body10","parent":"Body3","length":139.37,"rotation":98.05,"x":6.36,"y":87.59},{"name":"Body11","parent":"Body3","length":135.14,"rotation":120.72,"x":-158.01,"y":100.72},{"name":"Body22","parent":"Body2","length":106.6,"rotation":113.73,"x":332.53,"y":208.01},{"name":"Body23","parent":"Body2","length":138.2,"rotation":133.11,"x":208.03,"y":195.13},{"name":"Leg_Ctrl","parent":"Body","length":600.58,"rotation":90.69,"x":658.74,"y":276.77},{"name":"Body14","parent":"Body","length":164.15,"rotation":-175.43,"x":-97.75,"y":65.11},{"name":"Eff","parent":"_chr","x":-333.78,"y":1918.51},{"name":"Eff2","parent":"Eff","x":697.17,"y":-723.62},{"name":"Eff3","parent":"Eff2","length":150.33,"rotation":-33.06,"x":49.45,"y":-36.66},{"name":"Eff4","parent":"Eff2","length":86.93,"rotation":-23.03,"x":143.45,"y":27.34},{"name":"Eff5","parent":"Eff","length":259.45,"rotation":139.06,"x":-262.54,"y":-274.34},{"name":"Eff6","parent":"Eff","length":199.7,"rotation":-150.61,"x":-278.1,"y":-901.86},{"name":"Face","parent":"Head","rotation":5.45,"x":334.8,"y":72.46},{"name":"Body15","parent":"Body","length":418.19,"rotation":142.7,"x":-2.24,"y":124.6},{"name":"Body16","parent":"Body15","length":570.51,"rotation":68.93,"x":713.58,"y":85.66},{"name":"_chr2","parent":"_chr","length":347.09,"rotation":-90.95,"x":-1166.94,"y":-28.43},{"name":"_chr3","parent":"_chr2","length":120.96,"rotation":0.95,"x":-28.6,"y":-14.97},{"name":"_chr4","parent":"_chr2","length":174.34,"rotation":-0.94,"x":-186.83,"y":-26.24,"scaleX":0.703,"scaleY":0.703},{"name":"_chr5","parent":"_chr2","length":144.79,"rotation":-0.72,"x":-218.54,"y":34.15},{"name":"_chr6","parent":"_chr2","length":400.05,"rotation":156.45,"x":-48.18,"y":-19.08,"scaleX":0.998,"scaleY":0.998},{"name":"Eff7","parent":"Eff","length":170.54,"rotation":-154.4,"x":-512.96,"y":-833.41},{"name":"Body17","parent":"Body3","length":239.4,"rotation":-67.62,"x":641.6,"y":107.17,"scaleX":1.438,"scaleY":1.079},{"name":"AT_Down","parent":"_chr","length":136.36,"rotation":-90,"x":-1239.2,"y":4,"scaleY":1.453},{"name":"Eff8","parent":"Eff","length":236.96,"rotation":-147.85,"x":-430.18,"y":-1000.11},{"name":"Eff9","parent":"Eff","length":236.96,"rotation":-141.33,"x":-125.54,"y":-871.59,"scaleX":0.88,"scaleY":0.88},{"name":"Eff10","parent":"Eff","length":236.96,"rotation":-165.14,"x":-715.78,"y":-671.67,"scaleX":0.88,"scaleY":0.88}],"slots":[{"name":"_Shadow","bone":"_Shadow"},{"name":"body3","bone":"Body14","attachment":"body2"},{"name":"leg_R6","bone":"Body23","attachment":"leg_R6"},{"name":"leg_R5","bone":"Body22","attachment":"leg_R5"},{"name":"leg_R4","bone":"Body11","attachment":"leg_R4"},{"name":"leg_R3","bone":"Body10","attachment":"leg_R3"},{"name":"leg_R2","bone":"Body9","attachment":"leg_R2"},{"name":"leg_R1","bone":"Body8","attachment":"leg_R1"},{"name":"tale2","bone":"Body7","attachment":"tale2"},{"name":"tale1","bone":"Tale","attachment":"tale1"},{"name":"mask","bone":"_chr","attachment":"mask"},{"name":"body","bone":"Body","attachment":"body"},{"name":"body2","bone":"Body4","attachment":"body2"},{"name":"leg_L14","bone":"Leg21","attachment":"leg_L14"},{"name":"leg_L13","bone":"Leg20","attachment":"leg_L13"},{"name":"leg_L12","bone":"Leg19","attachment":"leg_L12"},{"name":"body_AT","bone":"Body"},{"name":"leg_AT","bone":"Body"},{"name":"AT_eff_1","bone":"_chr6","color":"ffffff00"},{"name":"eff_2_2","bone":"_chr3"},{"name":"eff_2_2sm","bone":"_chr5","color":"ffffff00"},{"name":"AT_jimen","bone":"AT_Down"},{"name":"eff_2_2bg","bone":"_chr4","color":"ffffff00"},{"name":"leg_L11","bone":"Leg18","attachment":"leg_L11"},{"name":"leg_L10","bone":"Leg17","attachment":"leg_L10"},{"name":"leg_L9","bone":"Leg16","attachment":"leg_L9"},{"name":"leg_L8","bone":"Leg15","attachment":"leg_L8"},{"name":"leg_L7","bone":"Leg14","attachment":"leg_L7"},{"name":"leg_L6","bone":"Body13","attachment":"leg_L6"},{"name":"leg_L5","bone":"Body12","attachment":"leg_L5"},{"name":"leg_L4","bone":"Leg_L4","attachment":"leg_L4"},{"name":"leg_L3","bone":"Leg_L3","attachment":"leg_L3"},{"name":"leg_L2","bone":"Leg_L2","attachment":"leg_L2"},{"name":"leg_L1","bone":"Leg_L1","attachment":"leg_L1"},{"name":"head_default","bone":"Head","attachment":"head_default"},{"name":"head_default_V","bone":"Head","attachment":"head_default_V"},{"name":"eye_default","bone":"Face","attachment":"eye_default"},{"name":"head_AT1","bone":"Head"},{"name":"eff_1","bone":"Eff5"},{"name":"eff_2","bone":"Eff6"},{"name":"head_AT2","bone":"Head"},{"name":"head_AT3","bone":"Head"},{"name":"eff_face","bone":"Body17"},{"name":"eff_sand_2","bone":"Eff8"},{"name":"eff_sand_6","bone":"Eff9"},{"name":"eff_sand_7","bone":"Eff10"},{"name":"eff_sand_3","bone":"Eff7"},{"name":"eff_sand_4","bone":"Eff3"},{"name":"eff_sand_5","bone":"Eff4"}],"transform":[{"name":"Body2","order":7,"bones":["Body14"],"target":"Body2","rotation":68,"x":-76.46,"y":86.26,"shearY":360,"rotateMix":0.306,"translateMix":0,"scaleMix":0,"shearMix":0},{"name":"Leg9","order":9,"bones":["Leg19"],"target":"Leg_Ctrl","rotation":-167.06,"x":-205.03,"y":-232.83,"shearY":360,"rotateMix":-1.5,"translateMix":0,"shearMix":0},{"name":"Leg14","order":3,"bones":["Leg14"],"target":"Leg_Ctrl","rotation":162.03,"x":-182.59,"y":407.94,"shearY":360,"rotateMix":0.878,"translateMix":0,"shearMix":0},{"name":"Leg15","order":4,"bones":["Leg15"],"target":"Leg_Ctrl","rotation":-124.66,"x":-173.38,"y":335.25,"shearY":360,"rotateMix":1.2,"translateMix":0,"shearMix":0},{"name":"Leg16","order":5,"bones":["Leg16"],"target":"Leg_Ctrl","rotation":-125.51,"x":-164.95,"y":198.05,"shearY":360,"translateMix":0,"shearMix":0},{"name":"Leg17","order":6,"bones":["Leg17"],"target":"Leg_Ctrl","rotation":-157.13,"x":-130.59,"y":36.35,"shearY":360,"rotateMix":0.73,"translateMix":0,"shearMix":0},{"name":"Leg18","order":8,"bones":["Leg18"],"target":"Leg_Ctrl","rotation":-160.31,"x":-156.78,"y":-76.15,"shearY":360,"rotateMix":-1,"translateMix":0,"shearMix":0},{"name":"Leg20","order":10,"bones":["Leg20"],"target":"Leg_Ctrl","rotation":-160.7,"x":-208.28,"y":-335.62,"shearY":360,"rotateMix":-1.4,"translateMix":0,"shearMix":0},{"name":"Leg21","order":11,"bones":["Leg21"],"target":"Leg_Ctrl","rotation":-123.26,"x":-193.04,"y":-410.4,"shearY":360,"rotateMix":-1,"translateMix":0,"shearMix":0},{"name":"Mouth","order":1,"bones":["Mouth_L"],"target":"Mouth","rotation":-0.15,"x":-215.78,"y":393.16,"rotateMix":-1,"translateMix":0,"scaleMix":0,"shearMix":0},{"name":"Tale","order":2,"bones":["Body7"],"target":"Tale","rotation":38.33,"x":-6.98,"y":29.15,"rotateMix":1.7,"translateMix":0,"scaleMix":0,"shearMix":0},{"name":"V_","order":0,"bones":["Head4"],"target":"Head3","rotation":-51.02,"x":4.67,"y":-41.85,"shearY":360,"rotateMix":-1,"translateMix":0,"shearMix":0}],"skins":{"default":{"AT_eff_1":{"AT_eff_1":{"x":465.88,"y":-8.74,"rotation":-65.5,"width":721,"height":950}},"AT_jimen":{"AT_jimen":{"x":-16.54,"y":75.43,"rotation":90,"width":672,"height":70}},"body":{"body":{"type":"mesh","uvs":[0,0,1,0,0.99999,0.43363,0.81631,0.65428,0.83224,0.77852,0.94988,0.84916,1,1,0.33399,0.99999,0.18165,0.9006,0.12391,0.77683,0.1689,0.64418,0.29315,0.52462,0.41474,0.40763,0.38093,0.28725,0,0.18508,0.60843,0.92407,0.48586,0.81802,0.47272,0.67727,0.3736,0.14868],"triangles":[14,0,18,18,0,1,14,18,13,1,2,13,2,12,13,11,12,2,3,11,2,17,11,3,16,17,3,17,10,11,16,10,17,13,18,1,16,3,4,9,10,16,8,9,16,15,16,4,15,4,5,7,8,16,7,16,15,15,5,6,7,15,6],"vertices":[3,6,766.71,569.49,0.12077,7,210.94,507.28,0.112,8,330.47,-266.49,0.76723,2,6,947.06,-28.92,0.56,8,-291.14,-331.44,0.44,4,5,640.26,-453.76,0.08565,6,357.91,-206.47,0.44965,7,-197.86,-268.68,0.2807,8,-355.07,280.55,0.184,2,5,411.54,-211.05,0.62613,6,24.99,-186.9,0.37387,1,5,249.41,-141.11,1,1,5,126.87,-162.04,1,3,5,-78.58,-94.34,0.02093,6,-411.59,-438.38,0.128,4,64.74,143.98,0.85107,1,5,107.59,277.96,1,2,5,276.31,300.05,0.80368,6,-424.13,92.03,0.19632,2,5,449.54,253.78,0.58809,6,-266.37,177.27,0.41191,2,5,605.33,144.45,0.60192,6,-78.03,204.66,0.39808,3,5,722.33,-0.88,0.29565,6,106.81,179.26,0.5871,7,-448.96,117.04,0.11726,3,5,836.83,-143.09,0.12902,6,287.68,154.4,0.63898,7,-268.08,92.19,0.232,2,6,445.15,223.92,0.76,8,51.33,114.17,0.24,2,6,515.26,493.71,0.744,8,303.19,-5.29,0.256,3,5,127.23,76.37,0.79488,6,-379.04,-172.96,0.06912,4,-179.99,251.72,0.136,2,5,296.09,77.59,0.58302,6,-257.07,-56.19,0.41698,2,5,478.4,-4.39,0.272,6,-68.21,9.3,0.728,2,6,632.08,285.04,0.24,8,76.31,-80.91,0.76],"hull":15}},"body2":{"body2":{"type":"mesh","uvs":[1.0E-5,0.34519,0,0.24373,0.24001,0,0.26275,0.16031,0.34579,0.31529,0.40955,0.32922,0.53758,0.131,0.60833,0.08011,0.68334,0.17965,0.78826,0.50397,0.87811,0.51264,1,0.22128,1,0.71129,0.90199,1,0.76855,1,0.71638,0.91821,0.61175,0.75418,0.4229,0.99994,0.29652,0.99997,0.22471,1,0.13909,0.83429,0.0575,0.62543,0.3412,0.69222,0.42639,0.67062,0.22594,0.43821,0.23762,0.62726],"triangles":[19,20,25,25,24,22,4,24,3,18,19,22,17,18,22,25,22,19,17,23,16,17,22,23,5,23,22,4,5,22,23,5,16,4,22,24,21,24,25,21,0,24,3,24,1,24,0,1,1,2,3,20,21,25,6,16,5,16,6,7,14,9,10,16,9,15,14,15,9,8,9,16,16,7,8,10,12,13,14,10,13,10,11,12],"vertices":[1,5,194.45,282.3,1,1,5,232.43,267.97,1,1,5,144.69,-127.21,1,2,5,55.73,-142.73,0.504,4,47.95,285.75,0.496,3,13,30.01,134.81,0.24,5,-56.26,-242.99,0.13984,4,187.71,230.42,0.62016,2,13,133.42,105.76,0.49468,4,295.01,225.45,0.50532,2,14,-209.76,39.2,0.22379,13,359.31,126.09,0.77621,2,14,-105.55,99.58,0.45349,13,479.41,116.92,0.54651,3,15,-190.9,311.83,0.01586,14,24.95,112.59,0.67143,13,594.38,53.82,0.31271,2,15,-71.1,137.95,0.03708,14,231.62,69.27,0.96292,2,15,67.76,77.98,0.85928,14,373.53,121.6,0.14072,1,15,296.98,96.84,1,1,15,230.93,-65.14,1,2,15,39.27,-98.3,0.99963,14,474.47,-25.71,3.7E-4,1,14,265.39,-107.7,1,2,14,172.98,-112.57,0.88386,13,589.07,-215.59,0.11614,3,14,-12.32,-122.35,0.5364,13,430.73,-118.82,0.2876,4,635.32,73.74,0.176,2,13,101.29,-132.58,0.576,4,317.47,-14,0.424,1,4,104.79,-14.01,1,2,5,-183.76,48.6,0.12,4,-16.08,-14.02,0.88,1,5,-66.4,151.03,1,2,5,61.73,240.52,0.952,4,-297.52,119.72,0.048,3,13,-7.88,5.46,0.544,5,-173.16,-175.89,0.06599,4,179.97,95.86,0.39001,3,14,-313.65,-208.47,0.1807,13,133.54,-19.37,0.22689,4,323.35,103.57,0.59241,2,5,-4.25,-42.6,0.4,4,-14.78,187.32,0.6,1,4,5.66,119.05,1],"hull":22}},"body3":{"body2":{"type":"mesh","uvs":[0.19893,0.76695,0.1291,0.95222,0.01217,0.8512,0.12445,0.69564,0.12987,0.79716],"triangles":[4,3,0,4,2,3,1,2,4,1,4,0],"vertices":[-220.22,6.09,83.94,55.56,277.23,3.95,54.37,-41.38,51.62,0.14],"hull":4}},"body_AT":{"body_AT":{"type":"mesh","uvs":[0,0.62833,0.03242,0.02299,0.27377,0.01903,0.36219,0.10416,0.43671,0.35896,0.48209,0.52888,0.53206,0.60331,0.61635,0.52827,0.69942,0.47324,0.78127,0.66835,0.85334,0.63333,0.861,0.18708,0.92266,0.1744,0.94202,1.0E-5,1,0,1,0.67335,0.9242,0.80343,0.85457,1,0.7605,1,0.69698,0.86846,0.57237,1,0.32488,0.9461,0.37681,0.82915,0.35403,0.79184,0.30126,0.66168,0.23887,0.60331,0.19367,1,0,1,0.52772,0.86894,0.95518,0.40225,0.92808,0.61787,0.88007,0.78909,0.25773,0.36227,0.36612,0.5113,0.46601,0.77765],"triangles":[11,29,10,16,31,15,31,30,15,30,29,15,30,10,29,15,29,14,11,12,29,29,12,14,14,12,13,16,17,31,17,18,31,31,10,30,31,18,9,8,9,19,18,19,9,9,10,31,7,19,20,28,7,20,19,7,8,28,6,7,28,34,6,20,21,28,28,21,22,22,34,28,6,34,5,22,23,34,23,24,34,33,34,24,5,34,33,24,25,33,25,0,32,25,32,33,5,33,4,33,32,4,32,3,4,32,2,3,32,1,2,25,26,0,27,0,26,32,0,1],"vertices":[1,48,772.84,-178.23,1,1,48,465.46,-496.52,1,1,47,784.6,-88.38,1,2,47,542.11,-196.71,0.848,4,-314.23,609.61,0.152,2,47,258.53,-184.06,0.68,4,-96.34,427.68,0.32,2,47,79.45,-167.97,0.46015,4,36.36,306.36,0.53985,2,4,182.48,253.21,0.688,13,30.06,158.2,0.312,2,47,-232.56,-406.24,0.00114,13,282.26,154.79,0.99886,2,13,527.76,138.27,0.34772,14,-77.75,144.54,0.65228,3,14,195.91,102.22,0.93159,15,-74.24,186.43,0.0528,17,-138.7,320.66,0.01561,3,14,382.98,202.44,0.03639,15,130.35,130.01,0.46166,17,-29.46,138.71,0.50195,1,17,270.31,248.98,1,1,16,214.8,317.03,1,1,16,322.42,401.43,1,1,16,472.88,323.28,1,2,16,251.25,-103.36,0.99901,17,120.36,-264.1,9.9E-4,2,15,276.33,-60.67,0.45541,16,11.74,-83.6,0.54459,1,15,34.8,-113.76,1,1,14,225.83,-140.4,1,2,13,457.14,-135.03,0.32023,14,18.62,-120.78,0.67977,2,4,300.36,-30.02,0.01996,13,81,-144.33,0.98004,1,4,-423.3,8.47,1,2,47,194.38,189.11,0.08,4,-271.46,91.97,0.92,1,47,263.52,208.3,1,1,47,442.56,227.88,1,1,47,612.93,305.29,1,1,48,429.84,344.72,1,1,48,912.02,47.72,1,1,4,169.78,63.56,1,1,16,224.18,128.83,1,4,14,582.39,292.5,0.0164,15,336.86,57.73,0.20814,16,82.89,28.74,0.47751,17,70.24,-56.06,0.29795,4,14,496.35,127.44,0.01497,15,160.72,-2.48,0.43283,16,-98.03,-15.04,0.33852,17,-98.83,21.82,0.21368,2,48,31.58,55.24,0.032,47,673.38,134.99,0.968,2,47,356.77,27.54,0.92,4,-302.71,318.91,0.08,1,47,9.21,1.81,1],"hull":28}},"eff_1":{"eff_1":{"x":105.04,"y":-13.23,"rotation":-139.06,"width":478,"height":371}},"eff_2":{"eff_2":{"x":175.73,"y":55.01,"rotation":150.61,"width":290,"height":546}},"eff_2_2":{"eff_2_2":{"x":-146.08,"y":38.43,"rotation":90,"width":944,"height":332}},"eff_2_2bg":{"eff_2_2bg":{"x":-186.25,"y":57.95,"rotation":91.89,"width":1402,"height":674}},"eff_2_2sm":{"eff_2_2sm":{"x":-115.91,"y":47.44,"rotation":91.1,"width":979,"height":466}},"eff_face":{"eff_face":{"x":-17.69,"y":7.45,"width":478,"height":233}},"eff_sand_2":{"eff_sand_2":{"x":97.28,"y":-24.22,"rotation":147.85,"width":303,"height":203}},"eff_sand_3":{"eff_sand_3":{"x":70.04,"y":0.94,"rotation":154.4,"width":187,"height":69}},"eff_sand_4":{"eff_sand_4":{"x":61.93,"y":-17.86,"rotation":33.06,"width":292,"height":160}},"eff_sand_5":{"eff_sand_5":{"x":39.89,"y":-3.96,"rotation":23.03,"width":130,"height":89}},"eff_sand_6":{"eff_sand_2":{"x":97.28,"y":-24.22,"rotation":147.85,"width":303,"height":203}},"eff_sand_7":{"eff_sand_2":{"x":97.28,"y":-24.22,"rotation":147.85,"width":303,"height":203}},"eye_default":{"eye_damage":{"x":-22.89,"y":-71.37,"rotation":-179.49,"width":422,"height":227},"eye_default":{"x":-27.4,"y":-69.91,"rotation":-179.49,"width":395,"height":230}},"head_AT1":{"head_AT1":{"x":227.73,"y":-129.93,"rotation":-174.04,"width":776,"height":757}},"head_AT2":{"head_AT2":{"x":-258.92,"y":-192.33,"rotation":-174.04,"width":737,"height":666}},"head_AT3":{"head_AT3":{"x":233.48,"y":-136.87,"rotation":-174.04,"width":710,"height":682}},"head_default":{"head_default":{"type":"mesh","uvs":[0.00398,0.56095,0,0.87232,0.10285,1,0.34675,1,0.22151,0.77866,0.39948,0.93814,0.73567,0.93814,0.80158,0.8065,0.75324,1,1,1,1,0.65715,1,0,0,0,0.47404,0.53855,0.16664,0.63162,0.88001,0.71056],"triangles":[15,10,9,6,5,7,5,13,7,5,4,13,1,14,4,1,0,14,7,13,15,4,14,13,15,13,10,13,11,10,13,14,12,14,0,12,13,12,11,2,1,4,8,7,9,7,15,9,3,2,4],"vertices":[1,8,587.04,81.92,1,2,9,150.91,-28.27,0.456,8,571.14,259.33,0.544,2,9,173.07,68.87,0.56,8,496.14,324.93,0.44,3,9,82.53,201.67,0.808,10,-104.46,-349.38,0,8,336.28,308.22,0.192,2,9,24.41,62.15,0.392,8,431.52,190.88,0.608,2,9,33.71,210.45,0.144,8,305.39,269.42,0.856,2,10,53.53,-144.5,0.32,8,85.05,246.4,0.68,2,10,31.73,-60.34,0.496,8,49.67,167,0.504,2,10,86.59,-161.61,0.752,8,69.85,280.39,0.248,2,10,202.57,-47.63,0.6,8,-91.88,263.49,0.4,1,8,-71.5,68.44,1,1,8,-32.45,-305.41,1,1,8,622.99,-236.93,1,2,9,-182.81,122.28,0.096,8,280.27,36.99,0.904,1,8,476.22,110.98,1,2,10,30.12,15.03,0.496,8,3.96,107.04,0.504],"hull":13}},"head_default_V":{"head_default_V":{"type":"mesh","uvs":[0,0.00336,0.06915,0,0.40472,0.74962,0.828,0,1,0,1,0.14398,0.48861,1,0.37803,1,0,0.28866],"triangles":[7,2,6,6,2,5,7,8,2,3,4,5,2,3,5,8,0,1,1,2,8],"vertices":[1,11,365.92,-23.71,1,1,11,355.25,-47.34,1,1,8,393.15,-123.18,1,1,12,363.5,56.75,1,1,12,396.54,1.36,1,1,12,343.98,-29.99,1,1,8,350.81,-20.62,1,1,8,392.05,-16.31,1,1,11,254.11,26.77,1],"hull":9}},"leg_AT":{"leg_AT":{"type":"mesh","uvs":[0,0,0.10158,0,0.21949,0.20128,0.40996,0.72374,0.57535,0.59084,0.70611,0.48697,0.88348,0.64162,0.99999,0.62067,1,1,0.84417,1,0.7104,0.89807,0.53378,1,0.42908,0.99999,0.3866,0.99999,0.26644,1,0.16409,0.5938,0,0.44333],"triangles":[6,7,8,9,6,8,9,10,6,6,10,5,5,10,4,10,11,3,11,12,3,3,4,10,2,0,1,2,16,0,15,16,2,13,14,3,3,14,15,2,3,15,13,3,12],"vertices":[1,48,60.04,69.82,1,1,48,-95.64,165.71,1,2,47,302.81,-3.16,0.664,48,-230.54,351.39,0.336,3,47,-107.32,-30.58,0.25404,4,101.66,83.88,0.2514,13,-86.88,11.46,0.49456,1,13,216.17,0.49,1,2,13,455.63,-8.69,0.14216,14,-54.09,-17.45,0.85784,2,14,267.64,36.62,0.73357,15,-67.53,89.46,0.26643,2,14,459.57,121.65,0.00273,15,130.1,18.69,0.99727,1,15,67.96,-133.76,1,1,14,258.56,-134.01,1,2,13,422.9,-184.26,0.22377,14,18.24,-180.74,0.77623,3,4,324.54,-36.02,1.0E-5,13,103.2,-155.63,0.99946,14,-261.58,-337.99,5.3E-4,3,47,-207.36,43.93,0.01684,4,136.08,-36.02,0.30367,13,-80.4,-113.11,0.67949,1,47,-146.54,90.27,1,2,47,25.5,221.35,0.992,4,-156.67,-36.02,0.008,3,47,278.88,192.77,0.70034,48,-56.3,444.15,0.264,4,-340.89,140.27,0.03566,1,48,160.94,233.64,1],"hull":17}},"leg_L1":{"leg_L1":{"x":94.83,"y":0.83,"rotation":-7.77,"width":177,"height":71}},"leg_L10":{"leg_L10":{"x":41.18,"y":-15.98,"rotation":66.45,"width":101,"height":115}},"leg_L11":{"leg_L11":{"x":48.66,"y":-13.83,"rotation":70.33,"width":86,"height":95}},"leg_L12":{"leg_L12":{"x":46.6,"y":-5.4,"rotation":76.37,"width":76,"height":82}},"leg_L13":{"leg_L13":{"x":47.17,"y":-10.86,"rotation":70.02,"width":74,"height":79}},"leg_L14":{"leg_L14":{"x":27.34,"y":-11.56,"rotation":32.57,"width":94,"height":74}},"leg_L2":{"leg_L2":{"x":98.86,"y":-11.82,"rotation":12.99,"width":168,"height":116}},"leg_L3":{"leg_L3":{"x":74.27,"y":-6.77,"rotation":14.32,"width":143,"height":118}},"leg_L4":{"leg_L4":{"x":77.89,"y":-5.63,"rotation":14.86,"width":133,"height":110}},"leg_L5":{"leg_L5":{"x":76.52,"y":-2.63,"rotation":7.43,"width":153,"height":82}},"leg_L6":{"leg_L6":{"x":66.94,"y":-10.36,"rotation":38.93,"width":123,"height":151}},"leg_L7":{"leg_L7":{"x":55.1,"y":-12.42,"rotation":107.28,"width":119,"height":124}},"leg_L8":{"leg_L8":{"x":47.73,"y":-6.23,"rotation":33.98,"width":115,"height":102}},"leg_L9":{"leg_L9":{"x":54.07,"y":-7.86,"rotation":34.82,"width":130,"height":108}},"leg_R1":{"leg_R1":{"x":81.25,"y":1.73,"rotation":174.47,"width":273,"height":76}},"leg_R2":{"leg_R2":{"x":75.16,"y":4.29,"rotation":-158.02,"width":229,"height":107}},"leg_R3":{"leg_R3":{"x":53.46,"y":1.06,"rotation":-171.28,"width":216,"height":90}},"leg_R4":{"leg_R4":{"x":63.15,"y":-2.97,"rotation":166.05,"width":180,"height":100}},"leg_R5":{"leg_R5":{"x":55.15,"y":14.97,"rotation":129.7,"width":116,"height":155}},"leg_R6":{"leg_R6":{"x":93.85,"y":-14.73,"rotation":110.32,"width":165,"height":184}},"mask":{"mask":{"type":"clipping","end":"eff_2_2bg","vertexCount":6,"vertices":[-2973.52,-2.58,-560.21,-2.97,-461.43,-304.83,1693.68,-305.16,1719.51,2361.16,-2987.18,2376.01]}},"tale1":{"tale1":{"x":189.23,"y":159.05,"rotation":-27.45,"width":352,"height":553}},"tale2":{"tale2":{"type":"mesh","uvs":[0,0,1,0,1,0.59894,0.53386,0.96279,0.186,0.99662,0.45248,0.64772,0,0.64033],"triangles":[4,5,3,5,0,1,5,6,0,1,2,5,3,5,2],"vertices":[1,17,266.87,245.85,1,1,17,361.2,36.09,1,2,17,138.33,-64.14,0.99978,16,141.32,64.64,2.2E-4,1,15,243.21,0.55,1,1,15,180.47,8.3,1,1,17,68.54,42.55,1,1,17,28.6,138.7,1],"hull":7}}}},"events":{"Hit_1":{}},"animations":{"attack":{"slots":{"AT_eff_1":{"color":[{"time":1.2667,"color":"ffffff00","curve":[0.25,0,0.75,1]},{"time":1.3333,"color":"ffffffff","curve":"stepped"},{"time":1.4333,"color":"ffffffff"},{"time":1.5667,"color":"ffffff00"}],"attachment":[{"time":1.2667,"name":"AT_eff_1"}]},"AT_jimen":{"color":[{"time":0,"color":"ffffffff","curve":"stepped"},{"time":1.2667,"color":"ffffffff","curve":[0.25,0,0.75,1]},{"time":1.4,"color":"ffffff00"}],"attachment":[{"time":0,"name":null},{"time":0.9,"name":"AT_jimen"},{"time":1.4,"name":null}]},"body":{"attachment":[{"time":0.9,"name":null},{"time":1.3333,"name":"body"}]},"body2":{"attachment":[{"time":0.9,"name":null},{"time":1.3333,"name":"body2"}]},"body3":{"attachment":[{"time":0.9,"name":null},{"time":1.3333,"name":"body2"}]},"body_AT":{"attachment":[{"time":0.9,"name":"body_AT"},{"time":1.3333,"name":null}]},"eff_1":{"color":[{"time":0,"color":"ffffffff","curve":"stepped"},{"time":1.4667,"color":"ffffffff","curve":[0.586,0,0.75,1]},{"time":1.7333,"color":"ffffff00"}],"attachment":[{"time":1.4667,"name":"eff_1"}]},"eff_2":{"color":[{"time":0,"color":"ffffffff","curve":"stepped"},{"time":2.4667,"color":"ffffffff","curve":[0.25,0,0.75,1]},{"time":2.6667,"color":"ffffff00"}],"attachment":[{"time":2.4333,"name":"eff_2"}]},"eff_2_2":{"color":[{"time":1,"color":"ffffffff","curve":[0.25,0,0.75,1]},{"time":1.0667,"color":"ffffff00"}],"attachment":[{"time":0.9,"name":"eff_2_2"},{"time":1.0667,"name":null}]},"eff_2_2bg":{"color":[{"time":0,"color":"ffffff00","curve":"stepped"},{"time":0.9333,"color":"ffffff00","curve":[0.25,0,0.75,1]},{"time":1.0333,"color":"ffffffff"},{"time":1.1667,"color":"ffffff00"}],"attachment":[{"time":0.9333,"name":"eff_2_2bg"}]},"eff_2_2sm":{"color":[{"time":0,"color":"ffffff00","curve":"stepped"},{"time":0.9,"color":"ffffff00","curve":[0.25,0,0.75,1]},{"time":1,"color":"ffffffff","curve":[0.25,0,0.75,1]},{"time":1.3333,"color":"ffffff00"}],"attachment":[{"time":0.9,"name":"eff_2_2sm"}]},"eff_face":{"color":[{"time":2.5667,"color":"ffffffff","curve":[0.25,0,0.75,1]},{"time":2.6667,"color":"ffffff00"}],"attachment":[{"time":2.3667,"name":"eff_face"},{"time":2.6667,"name":"eff_face"}]},"eff_sand_2":{"color":[{"time":1.6,"color":"ffffffff","curve":[0.25,0,0.75,1]},{"time":1.6667,"color":"ffffff00"}],"attachment":[{"time":1.5,"name":"eff_sand_2"}]},"eff_sand_3":{"color":[{"time":2.5333,"color":"ffffffff","curve":[0.25,0,0.75,1]},{"time":2.6667,"color":"ffffff00"}],"attachment":[{"time":2.4333,"name":"eff_sand_3"}]},"eff_sand_4":{"color":[{"time":2.6,"color":"ffffffff","curve":[0.25,0,0.75,1]},{"time":2.7,"color":"ffffff00"}],"attachment":[{"time":2.5,"name":"eff_sand_4"}]},"eff_sand_5":{"color":[{"time":2.5,"color":"ffffffff"},{"time":2.6667,"color":"ffffff00"}],"attachment":[{"time":2.5,"name":"eff_sand_5"}]},"eff_sand_6":{"color":[{"time":1.4667,"color":"ffffffff","curve":[0.25,0,0.75,1]},{"time":1.6,"color":"ffffff00"}],"attachment":[{"time":1.4,"name":"eff_sand_2"}]},"eff_sand_7":{"color":[{"time":1.4,"color":"ffffffff","curve":[0.25,0,0.75,1]},{"time":1.5667,"color":"ffffff00"}],"attachment":[{"time":1.4,"name":"eff_sand_2"}]},"eye_default":{"attachment":[{"time":0.9,"name":null},{"time":1.3333,"name":null},{"time":2.7667,"name":"eye_default"}]},"head_AT1":{"color":[{"time":2.3333,"color":"ffffffff","curve":[0.25,0,0.75,1]},{"time":2.5,"color":"ffffff00"}],"attachment":[{"time":1.3333,"name":"head_AT1"},{"time":2.4667,"name":null}]},"head_AT2":{"color":[{"time":2.4333,"color":"ffffffff","curve":[0.25,0,0.75,1]},{"time":2.5333,"color":"ffffff00","curve":"stepped"},{"time":2.5667,"color":"ffffffff","curve":"stepped"},{"time":2.6,"color":"ffffffff","curve":[0.25,0,0.75,1]},{"time":2.6667,"color":"ffffff00","curve":"stepped"},{"time":2.7,"color":"ffffffff","curve":[0.25,0,0.75,1]},{"time":2.8333,"color":"ffffff00"}],"attachment":[{"time":2.4,"name":"head_AT2"}]},"head_AT3":{"color":[{"time":2.5333,"color":"ffffffff","curve":[0.25,0,0.75,1]},{"time":2.6,"color":"ffffff00","curve":"stepped"},{"time":2.6333,"color":"ffffffff","curve":[0.25,0,0.75,1]},{"time":2.7333,"color":"ffffff00","curve":"stepped"},{"time":2.7667,"color":"ffffffff"}],"attachment":[{"time":2.5,"name":"head_AT3"},{"time":2.7667,"name":null}]},"head_default":{"attachment":[{"time":0.9,"name":null},{"time":1.3333,"name":null},{"time":2.7667,"name":"head_default"}]},"head_default_V":{"attachment":[{"time":0.9,"name":null},{"time":1.3333,"name":null},{"time":2.7667,"name":"head_default_V"}]},"leg_AT":{"attachment":[{"time":0.9,"name":"leg_AT"},{"time":1.3333,"name":null}]},"leg_L1":{"attachment":[{"time":0.9,"name":null},{"time":1.3333,"name":"leg_L1"}]},"leg_L2":{"attachment":[{"time":0.9,"name":null},{"time":1.3333,"name":"leg_L2"}]},"leg_L3":{"attachment":[{"time":0.9,"name":null},{"time":1.3333,"name":"leg_L3"}]},"leg_L4":{"attachment":[{"time":0.9,"name":null},{"time":1.3333,"name":"leg_L4"}]},"leg_L5":{"attachment":[{"time":0.9,"name":null},{"time":1.3333,"name":"leg_L5"}]},"leg_L6":{"attachment":[{"time":0.9,"name":null},{"time":1.3333,"name":"leg_L6"}]},"leg_L7":{"attachment":[{"time":0.9,"name":null},{"time":1.3333,"name":"leg_L7"}]},"leg_L8":{"attachment":[{"time":0.9,"name":null},{"time":1.3333,"name":"leg_L8"}]},"leg_L9":{"attachment":[{"time":0.9,"name":null},{"time":1.3333,"name":"leg_L9"}]},"leg_L10":{"attachment":[{"time":0.9,"name":null},{"time":1.3333,"name":"leg_L10"}]},"leg_L11":{"attachment":[{"time":0.9,"name":null},{"time":1.3333,"name":"leg_L11"}]},"leg_L12":{"attachment":[{"time":0.9,"name":null},{"time":1.3333,"name":"leg_L12"}]},"leg_L13":{"attachment":[{"time":0.9,"name":null},{"time":1.3333,"name":"leg_L13"}]},"leg_L14":{"attachment":[{"time":0.9,"name":null},{"time":1.3333,"name":"leg_L14"}]},"leg_R1":{"attachment":[{"time":0.9,"name":null},{"time":1.3333,"name":"leg_R1"}]},"leg_R2":{"attachment":[{"time":0.9,"name":null},{"time":1.3333,"name":"leg_R2"}]},"leg_R5":{"attachment":[{"time":0.9,"name":null},{"time":1.3333,"name":"leg_R5"}]},"leg_R6":{"attachment":[{"time":0.9,"name":null},{"time":1.3333,"name":"leg_R6"}]},"tale1":{"attachment":[{"time":0.9,"name":null},{"time":1.3333,"name":"tale1"}]},"tale2":{"attachment":[{"time":0.9,"name":null},{"time":1.3333,"name":"tale2"}]}},"bones":{"Leg_Ctrl":{"rotate":[{"time":0,"angle":0,"curve":[0.25,0,0.75,1]},{"time":0.4667,"angle":12.09,"curve":[0.25,0,0.75,1]},{"time":1,"angle":0}]},"Tale":{"rotate":[{"time":0,"angle":0,"curve":[0.25,0,0.75,1]},{"time":0.5,"angle":-13.16,"curve":[0.25,0,0.75,1]},{"time":1,"angle":0,"curve":"stepped"},{"time":2.4,"angle":0,"curve":[0.26,0,0.618,0.44]},{"time":2.5333,"angle":-4.77,"curve":[0.329,0.32,0.671,0.68]},{"time":2.7,"angle":2.23,"curve":[0.382,0.56,0.74,1]},{"time":2.8667,"angle":-5.32},{"time":3.0333,"angle":0}]},"Body2":{"rotate":[{"time":0,"angle":0,"curve":[0.25,0,0.75,1]},{"time":0.2,"angle":7.78,"curve":[0.25,0,0.136,1]},{"time":0.6,"angle":-15.11,"curve":"stepped"},{"time":0.8,"angle":-15.11,"curve":[0.25,0,0.071,1]},{"time":1,"angle":32.37,"curve":"stepped"},{"time":1.2667,"angle":32.37,"curve":[0.379,0.6,0.524,1]},{"time":1.5,"angle":10.73,"curve":"stepped"},{"time":1.9667,"angle":10.73,"curve":[0.25,0,0.75,1]},{"time":2.2333,"angle":2.4,"curve":[0.25,0,0.75,1]},{"time":2.6333,"angle":3.83,"curve":[0.25,0,0.75,1]},{"time":3.0333,"angle":0}]},"Body3":{"rotate":[{"time":0,"angle":0,"curve":[0.25,0,0.75,1]},{"time":0.2667,"angle":12.01,"curve":[0.25,0,0.136,1]},{"time":0.6,"angle":-15.11,"curve":"stepped"},{"time":0.8333,"angle":-15.11,"curve":[0.258,0,0.619,0.45]},{"time":0.9,"angle":-0.53,"curve":"stepped"},{"time":1.3333,"angle":-0.53,"curve":[0.25,0,0.27,1]},{"time":1.5667,"angle":-19.14,"curve":"stepped"},{"time":2.3667,"angle":-19.14,"curve":[0.25,0,0.75,1]},{"time":2.4333,"angle":-25.05,"curve":[0.25,0,0.75,1]},{"time":2.5333,"angle":-14.9,"curve":[0.25,0,0.75,1]},{"time":2.6667,"angle":-19.61,"curve":[0.25,0,0.75,1]},{"time":3,"angle":0}]},"Body12":{"rotate":[{"time":0,"angle":0,"curve":[0.25,0,0.75,1]},{"time":0.2333,"angle":3.32,"curve":[0.25,0,0.75,1]},{"time":0.7,"angle":-30.02,"curve":[0.25,0,0.75,1]},{"time":1,"angle":0,"curve":"stepped"},{"time":3.0667,"angle":0,"curve":[0.25,0,0.75,1]},{"time":3.2667,"angle":-21.3,"curve":[0.25,0,0.75,1]},{"time":3.4333,"angle":0}]},"Leg_L4":{"rotate":[{"time":0,"angle":0},{"time":0.2333,"angle":6.62,"curve":[0.351,0.4,0.757,1]},{"time":0.7,"angle":-26.21,"curve":[0.25,0,0.75,1]},{"time":1,"angle":0,"curve":"stepped"},{"time":3,"angle":0,"curve":[0.25,0,0.75,1]},{"time":3.2,"angle":-21.3,"curve":[0.25,0,0.75,1]},{"time":3.4333,"angle":0}]},"Leg_L3":{"rotate":[{"time":0,"angle":0},{"time":0.2333,"angle":10.89,"curve":[0.333,0.33,0.758,1]},{"time":0.6667,"angle":-29.26,"curve":[0.25,0,0.75,1]},{"time":1,"angle":0,"curve":"stepped"},{"time":2.8667,"angle":0,"curve":[0.25,0,0.75,1]},{"time":3.1333,"angle":-21.3,"curve":[0.25,0,0.75,1]},{"time":3.3667,"angle":0}]},"Leg_L2":{"rotate":[{"time":0,"angle":0},{"time":0.1667,"angle":12.23,"curve":[0.351,0.4,0.757,1]},{"time":0.5,"angle":-34.45,"curve":[0.25,0,0.75,1]},{"time":1,"angle":0,"curve":"stepped"},{"time":2.8,"angle":0,"curve":[0.25,0,0.75,1]},{"time":3.0333,"angle":-21.3,"curve":[0.25,0,0.75,1]},{"time":3.3,"angle":0}]},"Leg_L1":{"rotate":[{"time":0,"angle":0,"curve":[0.25,0,0.75,1]},{"time":0.2,"angle":8.52,"curve":[0.25,0,0.75,1]},{"time":0.5333,"angle":-39.13,"curve":[0.25,0,0.75,1]},{"time":1,"angle":0,"curve":"stepped"},{"time":2.7,"angle":0,"curve":[0.25,0,0.75,1]},{"time":2.9333,"angle":-21.3,"curve":[0.25,0,0.75,1]},{"time":3.1667,"angle":0}]},"Body13":{"rotate":[{"time":0,"angle":0},{"time":0.2667,"angle":14.37},{"time":0.7333,"angle":-25.39},{"time":1,"angle":0,"curve":"stepped"},{"time":2.8,"angle":0,"curve":[0.25,0,0.75,1]},{"time":3.1333,"angle":-21.3,"curve":[0.25,0,0.75,1]},{"time":3.4333,"angle":0}]},"Body8":{"rotate":[{"time":0,"angle":0,"curve":[0.25,0,0.75,1]},{"time":0.1667,"angle":-5.62,"curve":[0.25,0,0.75,1]},{"time":0.5333,"angle":30.25,"curve":[0.25,0,0.75,1]},{"time":1,"angle":0,"curve":"stepped"},{"time":2.7667,"angle":0,"curve":[0.25,0,0.75,1]},{"time":2.9667,"angle":19.66,"curve":[0.25,0,0.75,1]},{"time":3.2,"angle":0}]},"Body9":{"rotate":[{"time":0,"angle":0,"curve":[0.25,0,0.75,1]},{"time":0.2333,"angle":-5.62,"curve":[0.25,0,0.75,1]},{"time":0.7,"angle":34.45,"curve":[0.25,0,0.75,1]},{"time":1,"angle":0,"curve":"stepped"},{"time":2.8333,"angle":0,"curve":[0.25,0,0.75,1]},{"time":3.0333,"angle":19.66,"curve":[0.25,0,0.75,1]},{"time":3.2667,"angle":0}]},"Body10":{"rotate":[{"time":0,"angle":0},{"time":0.3,"angle":-5.62,"curve":[0.25,0,0.75,1]},{"time":0.7333,"angle":23.89,"curve":[0.25,0,0.75,1]},{"time":1,"angle":0,"curve":"stepped"},{"time":2.9333,"angle":0,"curve":[0.25,0,0.75,1]},{"time":3.1333,"angle":19.66,"curve":[0.25,0,0.75,1]},{"time":3.3333,"angle":0}]},"Body11":{"rotate":[{"time":0,"angle":0,"curve":[0.25,0,0.75,1]},{"time":0.3333,"angle":-5.62,"curve":[0.25,0,0.75,1]},{"time":0.7667,"angle":23.89,"curve":[0.25,0,0.75,1]},{"time":1,"angle":0,"curve":"stepped"},{"time":3,"angle":0,"curve":[0.25,0,0.75,1]},{"time":3.2333,"angle":19.66,"curve":[0.25,0,0.75,1]},{"time":3.4667,"angle":0}]},"Body22":{"rotate":[{"time":0,"angle":0},{"time":0.3,"angle":-36.78,"curve":[0.216,0.23,0.75,1]},{"time":0.8333,"angle":9.82,"curve":[0.25,0,0.75,1]},{"time":1,"angle":0,"curve":"stepped"},{"time":3.0333,"angle":0,"curve":[0.25,0,0.75,1]},{"time":3.3,"angle":19.66,"curve":[0.25,0,0.75,1]},{"time":3.5,"angle":0}]},"Body23":{"rotate":[{"time":0,"angle":0,"curve":[0.25,0,0.75,1]},{"time":0.1667,"angle":-5.62,"curve":[0.25,0,0.75,1]},{"time":0.6,"angle":23.89,"curve":[0.25,0,0.75,1]},{"time":1,"angle":0,"curve":"stepped"},{"time":3.1667,"angle":0,"curve":[0.25,0,0.75,1]},{"time":3.3667,"angle":19.66,"curve":[0.25,0,0.75,1]},{"time":3.5667,"angle":0}]},"Body14":{"rotate":[{"time":0,"angle":17.05}],"translate":[{"time":0,"x":0,"y":0}]},"Mouth":{"rotate":[{"time":0,"angle":0,"curve":"stepped"},{"time":0.1333,"angle":0},{"time":0.2,"angle":-20.41},{"time":0.2667,"angle":10.71},{"time":0.3333,"angle":0},{"time":0.4,"angle":-20.41},{"time":0.4667,"angle":10.71},{"time":0.5667,"angle":0,"curve":"stepped"},{"time":2.8333,"angle":0,"curve":[0.25,0,0.75,1]},{"time":2.9667,"angle":-19.74,"curve":[0.25,0,0.75,1]},{"time":3.1333,"angle":9.21},{"time":3.3,"angle":0}]},"Head3":{"rotate":[{"time":0,"angle":0,"curve":[0.25,0,0.75,1]},{"time":0.3,"angle":7.93,"curve":[0.25,0,0.75,1]},{"time":0.7333,"angle":-5.86,"curve":[0.25,0,0.75,1]},{"time":1,"angle":0,"curve":"stepped"},{"time":2.8333,"angle":0,"curve":[0.25,0,0.75,1]},{"time":3.0333,"angle":6.75,"curve":[0.25,0,0.75,1]},{"time":3.1667,"angle":-8.01,"curve":[0.25,0,0.75,1]},{"time":3.3,"angle":0,"curve":[0.25,0,0.75,1]},{"time":3.4,"angle":-8.01,"curve":[0.25,0,0.75,1]},{"time":3.5,"angle":0,"curve":"stepped"},{"time":3.5667,"angle":0}]},"Head":{"rotate":[{"time":0,"angle":0,"curve":[0.25,0,0.75,1]},{"time":0.3667,"angle":5.39,"curve":[0.25,0,0.75,1]},{"time":0.7667,"angle":-7.47,"curve":[0.25,0,0.75,1]},{"time":1,"angle":0,"curve":[0.25,0,0.75,1]},{"time":1.3333,"angle":16.43,"curve":[0.25,0,0.75,1]},{"time":1.6333,"angle":27.57,"curve":"stepped"},{"time":2.0667,"angle":27.57,"curve":[0.25,0,0.168,1]},{"time":2.3333,"angle":-10.11,"curve":[0.27,0,0.618,0.41]},{"time":2.4,"angle":23.03,"curve":[0.348,0.38,0.695,0.76]},{"time":2.5667,"angle":17.8,"curve":"stepped"},{"time":2.8,"angle":17.8,"curve":[0.375,0.62,0.715,1]},{"time":3.0667,"angle":0,"curve":"stepped"},{"time":3.4333,"angle":0}]},"Body":{"scale":[{"time":0,"x":1,"y":1,"curve":[0.404,0,0.75,1]},{"time":0.5333,"x":1,"y":1.033,"curve":"stepped"},{"time":0.9,"x":1,"y":1.033,"curve":[0.25,0,0.75,1]},{"time":1.2667,"x":1,"y":1}]},"_chr3":{"scale":[{"time":0,"x":0.568,"y":1,"curve":"stepped"},{"time":0.9,"x":0.568,"y":1,"curve":[0.25,0,0.036,1]},{"time":1.0333,"x":2.834,"y":2.136}]},"Body15":{"rotate":[{"time":0,"angle":0.25},{"time":0.8333,"angle":0,"curve":[0.25,0,0.75,1]},{"time":1.0667,"angle":7.96,"curve":"stepped"},{"time":1.2667,"angle":7.96,"curve":[0.375,0.5,0.75,1]},{"time":1.4667,"angle":-31.76,"curve":"stepped"},{"time":2.5667,"angle":-31.76,"curve":"stepped"},{"time":2.8667,"angle":-31.76}]},"_chr6":{"scale":[{"time":0,"x":0.815,"y":1,"curve":"stepped"},{"time":1.2667,"x":0.815,"y":1,"curve":[0.466,0,0.752,0.39]},{"time":1.3333,"x":1.056,"y":1.336,"curve":[0.118,0.31,0.174,1]},{"time":1.5667,"x":1.151,"y":1.154}]},"_chr5":{"translate":[{"time":0,"x":0,"y":0,"curve":"stepped"},{"time":0.9,"x":0,"y":0,"curve":[0.25,0,0.75,1]},{"time":1.0667,"x":-327.17,"y":-5.43}],"scale":[{"time":0.9,"x":1,"y":1,"curve":[0.25,0,0.75,1]},{"time":1.3333,"x":2.691,"y":2.691}]},"_chr4":{"translate":[{"time":0,"x":0,"y":0}],"scale":[{"time":0,"x":1,"y":1,"curve":"stepped"},{"time":0.9333,"x":1,"y":1,"curve":[0.25,0,0,1]},{"time":1.2,"x":2.282,"y":1.559}]},"Body16":{"scale":[{"time":0,"x":1,"y":1,"curve":"stepped"},{"time":0.7667,"x":1,"y":1,"curve":[0.25,0,0.75,1]},{"time":0.9,"x":1,"y":0.995,"curve":[0.25,0,0.75,1]},{"time":1.0333,"x":1,"y":1}]},"Body17":{"scale":[{"time":0,"x":1,"y":1,"curve":"stepped"},{"time":2.3667,"x":1,"y":1.167,"curve":[0.25,0,0.17,1]},{"time":2.6333,"x":1.595,"y":1.188}]},"Body6":{"rotate":[{"time":0,"angle":0},{"time":2.9,"angle":-0.06}]},"Eff6":{"translate":[{"time":0,"x":0,"y":0,"curve":"stepped"},{"time":2.4333,"x":0,"y":0},{"time":2.5333,"x":-342.3,"y":-304.93,"curve":[0.165,0.4,0.377,1]},{"time":2.7,"x":-414.36,"y":-379.34}],"scale":[{"time":2.4333,"x":1,"y":1,"curve":[0.25,0,0.165,1]},{"time":2.6333,"x":1.569,"y":1.569}]},"Eff7":{"translate":[{"time":0,"x":0,"y":151.74,"curve":"stepped"},{"time":2.4333,"x":0,"y":151.74,"curve":[0.25,0,0.281,1]},{"time":2.5333,"x":-440.54,"y":189.41,"curve":[0.134,0.25,0.129,1]},{"time":2.7,"x":-745.5,"y":71.98}],"scale":[{"time":2.4333,"x":1,"y":1,"curve":[0.25,0,0.75,1]},{"time":2.6667,"x":1.887,"y":1.887}]},"Eff3":{"rotate":[{"time":0,"angle":0}],"translate":[{"time":0,"x":0,"y":0,"curve":"stepped"},{"time":2.5,"x":0,"y":0,"curve":[0.25,0,0,1]},{"time":2.7,"x":349.82,"y":-266.01}],"scale":[{"time":0,"x":1,"y":1}]},"Eff4":{"translate":[{"time":0,"x":0,"y":0,"curve":"stepped"},{"time":2.5,"x":0,"y":0,"curve":[0.25,0,0.75,1]},{"time":2.7,"x":539.31,"y":-389.91}]},"Eff8":{"translate":[{"time":0,"x":0,"y":0,"curve":"stepped"},{"time":1.5,"x":0,"y":0},{"time":1.6,"x":-232.89,"y":-94.34},{"time":1.7,"x":-318.57,"y":-180.02}]},"Eff9":{"translate":[{"time":0,"x":0,"y":0,"curve":"stepped"},{"time":1.4,"x":0,"y":0,"curve":[0.25,0,0.109,1]},{"time":1.6333,"x":-508.97,"y":-608.42}]},"Eff10":{"translate":[{"time":0,"x":0,"y":0,"curve":"stepped"},{"time":1.4,"x":0,"y":0,"curve":[0.25,0,0.109,1]},{"time":1.7333,"x":-356.65,"y":-32.46}]},"Eff5":{"translate":[{"time":0,"x":0,"y":0,"curve":"stepped"},{"time":1.4333,"x":0,"y":0,"curve":[0.25,0,0.75,1]},{"time":1.7667,"x":-145.26,"y":125.99}]}},"deform":{"default":{"body":{"body":[{"time":0,"curve":"stepped"},{"time":1.3333,"vertices":[66.68686,-50.35748,66.68768,-50.35767,-79.05713,-27.07874,-87.02509,-71.02521,-10.14417,111.86646],"curve":"stepped"},{"time":2.4,"vertices":[71.35471,-358.45905,71.35583,-358.45776,-360.35547,61.05969,11.91547,-81.38318,-80.28687,17.86609,0,0,0,0,0,0,0,0,0,0,0,0,0,0,0,0,0,0,0,0,0,0,0,0,0,0,0,0,0,0,0,0,0,0,0,0,0,0,0,0,0,0,0,0,0,0,0,0,32.65964,10.17395,-2.13184,-34.14172,114.58545,-224.06854,-250.19098,-27.22131],"curve":"stepped"},{"time":2.5,"vertices":[65.18826,-123.0116,65.19342,-123.00574,-138.1654,-17.07898,8.78754,-35.96118,-40.11191,7.62683,0,0,0,0,0,0,0,0,0,0,0,0,0,0,0,0,0,0,0,0,0,0,0,0,0,0,0,0,0,0,0,0,0,0,0,0,0,0,0,0,0,0,0,0,0,0,0,0,0,0,0,0,0,0,0,0,0,0,0,0,0,0,0,0,0,0,0,0,0,0,18.33801,-30.11694,-34.67426,-6.40356],"curve":"stepped"},{"time":2.5667,"vertices":[71.35471,-358.45905,71.35583,-358.45776,-360.35547,61.05969,11.91547,-81.38318,-80.28687,17.86609,0,0,0,0,0,0,0,0,0,0,0,0,0,0,0,0,0,0,0,0,0,0,0,0,0,0,0,0,0,0,0,0,0,0,0,0,0,0,0,0,0,0,0,0,0,0,0,0,32.65964,10.17395,-2.13184,-34.14172,114.58545,-224.06854,-250.19098,-27.22131],"curve":"stepped"},{"time":2.6333,"vertices":[65.18826,-123.0116,65.19342,-123.00574,-138.1654,-17.07898,8.78754,-35.96118,-40.11191,7.62683,0,0,0,0,0,0,0,0,0,0,0,0,0,0,0,0,0,0,0,0,0,0,0,0,0,0,0,0,0,0,0,0,0,0,0,0,0,0,0,0,0,0,0,0,0,0,0,0,0,0,0,0,0,0,0,0,0,0,0,0,0,0,0,0,0,0,0,0,0,0,18.33801,-30.11694,-34.67426,-6.40356],"curve":"stepped"},{"time":2.7,"vertices":[71.35471,-358.45905,71.35583,-358.45776,-360.35547,61.05969,11.91547,-81.38318,-80.28687,17.86609,0,0,0,0,0,0,0,0,0,0,0,0,0,0,0,0,0,0,0,0,0,0,0,0,0,0,0,0,0,0,0,0,0,0,0,0,0,0,0,0,0,0,0,0,0,0,0,0,32.65964,10.17395,-2.13184,-34.14172,114.58545,-224.06854,-250.19098,-27.22131],"curve":"stepped"},{"time":2.7667}]}}},"events":[{"time":0.9333,"name":"Hit_1"}]},"damage":{"slots":{"eye_default":{"attachment":[{"time":0,"name":"eye_damage"}]}},"bones":{"Body2":{"rotate":[{"time":0,"angle":-9.94}]},"Body3":{"rotate":[{"time":0,"angle":-17.13}]},"Head":{"rotate":[{"time":0,"angle":-13.86}]},"Body4":{"rotate":[{"time":0,"angle":6.98}]},"Body5":{"rotate":[{"time":0,"angle":-19.16}]},"Leg_L1":{"rotate":[{"time":0,"angle":26.26}]},"Leg_L2":{"rotate":[{"time":0,"angle":26.26}]},"Leg_L3":{"rotate":[{"time":0,"angle":26.26}]},"Leg_L4":{"rotate":[{"time":0,"angle":26.26}]},"Body12":{"rotate":[{"time":0,"angle":26.26}]},"Body13":{"rotate":[{"time":0,"angle":26.26}]},"Body8":{"rotate":[{"time":0,"angle":-31.52}]},"Body9":{"rotate":[{"time":0,"angle":-31.52}]},"Body10":{"rotate":[{"time":0,"angle":-31.52}]},"Body11":{"rotate":[{"time":0,"angle":-31.52}]},"Body22":{"rotate":[{"time":0,"angle":-31.52}]},"Body23":{"rotate":[{"time":0,"angle":-31.52}]},"Leg_Ctrl":{"rotate":[{"time":0,"angle":-48.24}]}}},"move":{"bones":{"Body":{"translate":[{"time":0,"x":0,"y":0,"curve":[0.25,0,0.75,1]},{"time":0.3667,"x":-26.89,"y":0,"curve":[0.25,0,0.75,1]},{"time":1,"x":0,"y":0}],"scale":[{"time":0,"x":1,"y":1,"curve":[0.404,0,0.75,1]},{"time":0.5333,"x":1,"y":0.957,"curve":[0.25,0,0.75,1]},{"time":1,"x":1,"y":1}]},"Leg_Ctrl":{"rotate":[{"time":0,"angle":0,"curve":[0.25,0,0.75,1]},{"time":0.2667,"angle":-27.93,"curve":[0.25,0,0.75,1]},{"time":0.7333,"angle":27.77,"curve":[0.25,0,0.75,1]},{"time":1,"angle":0}],"scale":[{"time":0,"x":1,"y":1,"curve":[0.25,0,0.75,1]},{"time":0.6333,"x":1.295,"y":1},{"time":1,"x":1,"y":1}]},"Body4":{"rotate":[{"time":0,"angle":0,"curve":[0.25,0,0.75,1]},{"time":0.5,"angle":4.22,"curve":[0.25,0,0.75,1]},{"time":1,"angle":0}],"translate":[{"time":0,"x":0,"y":0,"curve":[0.25,0,0.75,1]},{"time":0.4333,"x":-43.11,"y":0,"curve":[0.25,0,0.75,1]},{"time":1,"x":0,"y":0}]},"Body5":{"rotate":[{"time":0,"angle":0,"curve":[0.25,0,0.75,1]},{"time":0.5667,"angle":-12.11,"curve":[0.25,0,0.75,1]},{"time":1,"angle":0}],"translate":[{"time":0,"x":0,"y":0,"curve":[0.499,0,0.75,1]},{"time":0.2667,"x":-5.2,"y":1.46,"curve":[0.25,0,0.75,1]},{"time":0.7,"x":-37.22,"y":9.32},{"time":1,"x":0,"y":0}]},"Body6":{"rotate":[{"time":0,"angle":0,"curve":[0.25,0,0.75,1]},{"time":0.2667,"angle":-13.2,"curve":[0.25,0,0.75,1]},{"time":0.7,"angle":6.9,"curve":[0.25,0,0.75,1]},{"time":1,"angle":0}],"translate":[{"time":0,"x":0,"y":0,"curve":[0.25,0,0.75,1]},{"time":0.3333,"x":-15.98,"y":-27.16,"curve":[0.25,0,0.75,1]},{"time":0.7667,"x":48.96,"y":26.34,"curve":[0.25,0,0.75,1]},{"time":1,"x":0,"y":0}]},"Tale":{"rotate":[{"time":0,"angle":0},{"time":0.2667,"angle":17.26},{"time":0.7,"angle":-13.16},{"time":1,"angle":0}]},"Body2":{"rotate":[{"time":0,"angle":0},{"time":0.4333,"angle":-3.69},{"time":1,"angle":0}]},"Body3":{"rotate":[{"time":0,"angle":0,"curve":[0.25,0,0.75,1]},{"time":0.4,"angle":-10.22,"curve":[0.25,0,0.75,1]},{"time":1,"angle":0}]},"Head":{"rotate":[{"time":0,"angle":0,"curve":[0.25,0,0.75,1]},{"time":0.4333,"angle":10.85,"curve":[0.25,0,0.75,1]},{"time":1,"angle":0}]},"Body12":{"rotate":[{"time":0,"angle":0,"curve":[0.25,0,0.75,1]},{"time":0.2333,"angle":3.32,"curve":[0.25,0,0.75,1]},{"time":0.7,"angle":-30.02,"curve":[0.25,0,0.75,1]},{"time":1,"angle":0}]},"Leg_L4":{"rotate":[{"time":0,"angle":0},{"time":0.2333,"angle":6.62,"curve":[0.351,0.4,0.757,1]},{"time":0.7,"angle":-26.21,"curve":[0.25,0,0.75,1]},{"time":1,"angle":0}]},"Leg_L3":{"rotate":[{"time":0,"angle":0},{"time":0.2333,"angle":10.89,"curve":[0.333,0.33,0.758,1]},{"time":0.6667,"angle":-29.26,"curve":[0.25,0,0.75,1]},{"time":1,"angle":0}]},"Leg_L2":{"rotate":[{"time":0,"angle":0},{"time":0.1667,"angle":12.23,"curve":[0.351,0.4,0.757,1]},{"time":0.5,"angle":-34.45,"curve":[0.25,0,0.75,1]},{"time":1,"angle":0}]},"Leg_L1":{"rotate":[{"time":0,"angle":0,"curve":[0.25,0,0.75,1]},{"time":0.2,"angle":8.52,"curve":[0.25,0,0.75,1]},{"time":0.5333,"angle":-39.13,"curve":[0.25,0,0.75,1]},{"time":1,"angle":0}]},"Body13":{"rotate":[{"time":0,"angle":0},{"time":0.2667,"angle":14.37},{"time":0.7333,"angle":-25.39},{"time":1,"angle":0}]},"Body8":{"rotate":[{"time":0,"angle":0,"curve":[0.25,0,0.75,1]},{"time":0.1667,"angle":-5.62,"curve":[0.25,0,0.75,1]},{"time":0.5333,"angle":30.25,"curve":[0.25,0,0.75,1]},{"time":1,"angle":0}]},"Body9":{"rotate":[{"time":0,"angle":0,"curve":[0.25,0,0.75,1]},{"time":0.2333,"angle":-5.62,"curve":[0.25,0,0.75,1]},{"time":0.7,"angle":34.45,"curve":[0.25,0,0.75,1]},{"time":1,"angle":0}]},"Body10":{"rotate":[{"time":0,"angle":0},{"time":0.3,"angle":-5.62,"curve":[0.25,0,0.75,1]},{"time":0.7333,"angle":23.89,"curve":[0.25,0,0.75,1]},{"time":1,"angle":0}]},"Body11":{"rotate":[{"time":0,"angle":0,"curve":[0.25,0,0.75,1]},{"time":0.3333,"angle":-5.62,"curve":[0.25,0,0.75,1]},{"time":0.7667,"angle":23.89,"curve":[0.25,0,0.75,1]},{"time":1,"angle":0}]},"Body22":{"rotate":[{"time":0,"angle":0},{"time":0.3,"angle":-36.78,"curve":[0.216,0.23,0.75,1]},{"time":0.8333,"angle":9.82,"curve":[0.25,0,0.75,1]},{"time":1,"angle":0}]},"Body23":{"rotate":[{"time":0,"angle":0,"curve":[0.25,0,0.75,1]},{"time":0.1667,"angle":-5.62,"curve":[0.25,0,0.75,1]},{"time":0.6,"angle":23.89,"curve":[0.25,0,0.75,1]},{"time":1,"angle":0}]},"Body14":{"rotate":[{"time":0,"angle":0,"curve":[0.25,0,0.75,1]},{"time":0.3333,"angle":19.08,"curve":[0.245,0,0.637,0.56]},{"time":0.7,"angle":19.52,"curve":[0.381,0.55,0.742,1]},{"time":1,"angle":0}],"translate":[{"time":0,"x":0,"y":0},{"time":0.1667,"x":52.07,"y":-25.25},{"time":0.3667,"x":104.15,"y":0},{"time":0.7,"x":57.28,"y":34.72},{"time":1,"x":0,"y":0}]},"Mouth":{"rotate":[{"time":0,"angle":0,"curve":[0.25,0,0.75,1]},{"time":0.3,"angle":-20.41,"curve":[0.25,0,0.75,1]},{"time":0.8,"angle":19.22,"curve":[0.25,0,0.75,1]},{"time":1,"angle":0}]},"Head3":{"rotate":[{"time":0,"angle":0,"curve":[0.25,0,0.75,1]},{"time":0.3,"angle":7.93,"curve":[0.25,0,0.75,1]},{"time":0.7333,"angle":-5.86,"curve":[0.25,0,0.75,1]},{"time":1,"angle":0}]}}},"wait":{"bones":{"Leg_Ctrl":{"rotate":[{"time":0,"angle":0,"curve":[0.25,0,0.75,1]},{"time":0.4667,"angle":12.09,"curve":[0.25,0,0.75,1]},{"time":1,"angle":0}]},"Tale":{"rotate":[{"time":0,"angle":0,"curve":[0.25,0,0.75,1]},{"time":0.5,"angle":-13.16,"curve":[0.25,0,0.75,1]},{"time":1,"angle":0}]},"Body2":{"rotate":[{"time":0,"angle":0},{"time":0.4333,"angle":-1.62},{"time":1,"angle":0}]},"Body3":{"rotate":[{"time":0,"angle":0,"curve":[0.25,0,0.75,1]},{"time":0.5333,"angle":-4.23,"curve":[0.25,0,0.75,1]},{"time":1,"angle":0}]},"Body12":{"rotate":[{"time":0,"angle":0,"curve":[0.25,0,0.75,1]},{"time":0.2333,"angle":3.32,"curve":[0.25,0,0.75,1]},{"time":0.7,"angle":-30.02,"curve":[0.25,0,0.75,1]},{"time":1,"angle":0}]},"Leg_L4":{"rotate":[{"time":0,"angle":0},{"time":0.2333,"angle":6.62,"curve":[0.351,0.4,0.757,1]},{"time":0.7,"angle":-26.21,"curve":[0.25,0,0.75,1]},{"time":1,"angle":0}]},"Leg_L3":{"rotate":[{"time":0,"angle":0},{"time":0.2333,"angle":10.89,"curve":[0.333,0.33,0.758,1]},{"time":0.6667,"angle":-29.26,"curve":[0.25,0,0.75,1]},{"time":1,"angle":0}]},"Leg_L2":{"rotate":[{"time":0,"angle":0},{"time":0.1667,"angle":12.23,"curve":[0.351,0.4,0.757,1]},{"time":0.5,"angle":-34.45,"curve":[0.25,0,0.75,1]},{"time":1,"angle":0}]},"Leg_L1":{"rotate":[{"time":0,"angle":0,"curve":[0.25,0,0.75,1]},{"time":0.2,"angle":8.52,"curve":[0.25,0,0.75,1]},{"time":0.5333,"angle":-39.13,"curve":[0.25,0,0.75,1]},{"time":1,"angle":0}]},"Body13":{"rotate":[{"time":0,"angle":0},{"time":0.2667,"angle":14.37},{"time":0.7333,"angle":-25.39},{"time":1,"angle":0}]},"Body8":{"rotate":[{"time":0,"angle":0,"curve":[0.25,0,0.75,1]},{"time":0.1667,"angle":-5.62,"curve":[0.25,0,0.75,1]},{"time":0.5333,"angle":30.25,"curve":[0.25,0,0.75,1]},{"time":1,"angle":0}]},"Body9":{"rotate":[{"time":0,"angle":0,"curve":[0.25,0,0.75,1]},{"time":0.2333,"angle":-5.62,"curve":[0.25,0,0.75,1]},{"time":0.7,"angle":34.45,"curve":[0.25,0,0.75,1]},{"time":1,"angle":0}]},"Body10":{"rotate":[{"time":0,"angle":0},{"time":0.3,"angle":-5.62,"curve":[0.25,0,0.75,1]},{"time":0.7333,"angle":23.89,"curve":[0.25,0,0.75,1]},{"time":1,"angle":0}]},"Body11":{"rotate":[{"time":0,"angle":0,"curve":[0.25,0,0.75,1]},{"time":0.3333,"angle":-5.62,"curve":[0.25,0,0.75,1]},{"time":0.7667,"angle":23.89,"curve":[0.25,0,0.75,1]},{"time":1,"angle":0}]},"Body22":{"rotate":[{"time":0,"angle":0},{"time":0.3,"angle":-36.78,"curve":[0.216,0.23,0.75,1]},{"time":0.8333,"angle":9.82,"curve":[0.25,0,0.75,1]},{"time":1,"angle":0}]},"Body23":{"rotate":[{"time":0,"angle":0,"curve":[0.25,0,0.75,1]},{"time":0.1667,"angle":-5.62,"curve":[0.25,0,0.75,1]},{"time":0.6,"angle":23.89,"curve":[0.25,0,0.75,1]},{"time":1,"angle":0}]},"Body14":{"rotate":[{"time":0,"angle":17.05}],"translate":[{"time":0,"x":0,"y":0}]},"Mouth":{"rotate":[{"time":0,"angle":0,"curve":"stepped"},{"time":0.1333,"angle":0},{"time":0.2,"angle":-20.41},{"time":0.2667,"angle":10.71},{"time":0.3333,"angle":0},{"time":0.4,"angle":-20.41},{"time":0.4667,"angle":10.71},{"time":0.5667,"angle":0}]},"Head3":{"rotate":[{"time":0,"angle":0,"curve":[0.25,0,0.75,1]},{"time":0.3,"angle":7.93,"curve":[0.25,0,0.75,1]},{"time":0.7333,"angle":-5.86,"curve":[0.25,0,0.75,1]},{"time":1,"angle":0}]},"Head":{"rotate":[{"time":0,"angle":0,"curve":[0.25,0,0.75,1]},{"time":0.4667,"angle":5.39,"curve":[0.25,0,0.75,1]},{"time":1,"angle":0}]},"Body":{"scale":[{"time":0,"x":1,"y":1,"curve":[0.404,0,0.75,1]},{"time":0.5333,"x":1,"y":1.033,"curve":[0.25,0,0.75,1]},{"time":1,"x":1,"y":1}]}}}}}